.editorconfig
.gitignore
LICENSE
MANIFEST.in
README.md
mkdocs.yml
requirements.txt
requirements_dev.txt
requirements_docs.txt
setup.cfg
setup.py
.github/ISSUE_TEMPLATE/bug_report.md
.github/ISSUE_TEMPLATE/config.yml
.github/ISSUE_TEMPLATE/feature_request.md
.github/workflows/docs-build.yml
.github/workflows/docs.yml
.github/workflows/macos.yml
.github/workflows/pypi.yml
.github/workflows/ubuntu.yml
.github/workflows/windows.yml
TestingBm_123/TestingBm_123.py
TestingBm_123/__init__.py
TestingBm_123/common.py
TestingBm_123.egg-info/PKG-INFO
TestingBm_123.egg-info/SOURCES.txt
TestingBm_123.egg-info/dependency_links.txt
TestingBm_123.egg-info/not-zip-safe
TestingBm_123.egg-info/top_level.txt
docs/TestingBm_123.md
docs/changelog.md
docs/common.md
docs/contributing.md
docs/faq.md
docs/index.md
docs/installation.md
docs/usage.md
docs/examples/intro.ipynb
docs/overrides/main.html
my_utils/utils.py
tests/__init__.py
tests/test_TestingBm_123.py