Metadata-Version: 2.1
Name: TestingBm-123
Version: 0.0.4
Summary: testing bm
Home-page: https://github.com/youssefamroo/TestingBm_123
Author: youssef amr
Author-email: usef.amr11@gmail.com
License: MIT license
Keywords: TestingBm_123
Classifier: Intended Audience :: Developers
Classifier: License :: OSI Approved :: MIT License
Classifier: Natural Language :: English
Classifier: Programming Language :: Python :: 3
Classifier: Programming Language :: Python :: 3.8
Classifier: Programming Language :: Python :: 3.9
Classifier: Programming Language :: Python :: 3.10
Classifier: Programming Language :: Python :: 3.11
Requires-Python: >=3.8
License-File: LICENSE
